{
  "highlightr-plugin:Cyan": [
    {
      "modifiers": [
        "Mod",
        "Shift"
      ],
      "key": "H"
    }
  ],
  "obsidian-underline:toggle-link-heading": [
    {
      "modifiers": [
        "Mod",
        "Shift"
      ],
      "key": "1"
    }
  ],
  "obsidian-underline:toggle-center-tag": [
    {
      "modifiers": [
        "Mod",
        "Shift"
      ],
      "key": "C"
    }
  ],
  "obsidian-underline:toggle-underline-tag": [
    {
      "modifiers": [
        "Mod"
      ],
      "key": "U"
    }
  ],
  "obsidian-underline:toggle-link-block": [
    {
      "modifiers": [
        "Mod",
        "Shift"
      ],
      "key": "U"
    }
  ],
  "theme-picker:open-theme-picker": [
    {
      "modifiers": [
        "Mod",
        "Shift"
      ],
      "key": "Y"
    }
  ],
  "obsidian-excalidraw-plugin:toggle-lock": [],
  "obsidian-excalidraw-plugin:fullscreen": [
    {
      "modifiers": [],
      "key": "F11"
    }
  ],
  "app:toggle-left-sidebar": [
    {
      "modifiers": [
        "Mod"
      ],
      "key": "\\"
    }
  ],
  "app:open-vault": [
    {
      "modifiers": [
        "Mod",
        "Shift"
      ],
      "key": "V"
    }
  ]
}